MANIFEST.in
README.md
setup.cfg
setup.py
version.txt
bin/doxy
doxy/__init__.py
doxy/arg.py
doxy/debug.py
doxy/env.py
doxy/heritage.py
doxy/module.py
doxy/multiprocess.py
doxy/target.py
doxy/tools.py
doxy.egg-info/PKG-INFO
doxy.egg-info/SOURCES.txt
doxy.egg-info/dependency_links.txt
doxy.egg-info/not-zip-safe
doxy.egg-info/top_level.txt