Metadata-Version: 2.1
Name: doxy
Version: 0.3.2
Summary: Doxy is a simple wrapper over doxygen to generate multiple documentation for c++ library
Home-page: http://github.com/HeeroYui/doxy
Author: Edouard DUPIN
Author-email: yui.heero@gmail.com
License: APACHE-2
Keywords: documentation over doxygen
Platform: UNKNOWN
Classifier: Development Status :: 4 - Beta
Classifier: License :: OSI Approved :: Apache Software License
Classifier: Programming Language :: Python
Classifier: Topic :: Software Development :: Compilers
